flask_metrics_visitors/__init__.py
flask_metrics_visitors/models.py
flask_metrics_visitors/utils.py
flask_metrics_visitors/static/js/session-tracker.js
flask_metrics_visitors/templates/metrics/base.html
flask_metrics_visitors/templates/metrics/dashboard.html
flask_metrics_visitors/templates/metrics/session_analytics.html
flask_metrics_visitors-0.9.0.dist-info/METADATA
flask_metrics_visitors-0.9.0.dist-info/WHEEL
flask_metrics_visitors-0.9.0.dist-info/top_level.txt
flask_metrics_visitors-0.9.0.dist-info/RECORD
