Metadata-Version: 2.4
Name: flask-metrics-visitors
Version: 0.9.0
Summary: A Flask extension for tracking and visualizing visitor metrics
Home-page: https://github.com/yourusername/flask-metrics-visitors
Author: Patrick Hastings
Author-email: patrick@example.com
Classifier: Development Status :: 4 - Beta
Classifier: Environment :: Web Environment
Classifier: Framework :: Flask
Classifier: Intended Audience :: Developers
Classifier: License :: OSI Approved :: MIT License
Classifier: Operating System :: OS Independent
Classifier: Programming Language :: Python :: 3
Classifier: Programming Language :: Python :: 3.7
Classifier: Programming Language :: Python :: 3.8
Classifier: Programming Language :: Python :: 3.9
Classifier: Programming Language :: Python :: 3.10
Classifier: Topic :: Internet :: WWW/HTTP :: Dynamic Content
Classifier: Topic :: Software Development :: Libraries :: Python Modules
Requires-Python: >=3.7
Requires-Dist: Flask>=2.0.0
Requires-Dist: Flask-SQLAlchemy>=3.0.0
Requires-Dist: Flask-Login>=0.6.0
Requires-Dist: geopy>=2.4.1
Requires-Dist: user_agents>=2.2.0
Dynamic: author
Dynamic: author-email
Dynamic: classifier
Dynamic: description
Dynamic: description-content-type
Dynamic: home-page
Dynamic: requires-dist
Dynamic: requires-python
Dynamic: summary
